README.txt
setup.cfg
setup.py
Products/__init__.py
Products.QuillsEnabledRemoteBlogging.egg-info/PKG-INFO
Products.QuillsEnabledRemoteBlogging.egg-info/SOURCES.txt
Products.QuillsEnabledRemoteBlogging.egg-info/dependency_links.txt
Products.QuillsEnabledRemoteBlogging.egg-info/entry_points.txt
Products.QuillsEnabledRemoteBlogging.egg-info/namespace_packages.txt
Products.QuillsEnabledRemoteBlogging.egg-info/not-zip-safe
Products.QuillsEnabledRemoteBlogging.egg-info/requires.txt
Products.QuillsEnabledRemoteBlogging.egg-info/top_level.txt
Products/QuillsEnabledRemoteBlogging/LICENSE.txt
Products/QuillsEnabledRemoteBlogging/README.txt
Products/QuillsEnabledRemoteBlogging/__init__.py
Products/QuillsEnabledRemoteBlogging/config.py
Products/QuillsEnabledRemoteBlogging/configure.zcml
Products/QuillsEnabledRemoteBlogging/Extensions/Install.py
Products/QuillsEnabledRemoteBlogging/tests/__init__.py
Products/QuillsEnabledRemoteBlogging/tests/base.py
Products/QuillsEnabledRemoteBlogging/tests/test_docfile.py
Products/QuillsEnabledRemoteBlogging/tests/test_doctests.py
docs/HISTORY.txt
docs/INSTALL.txt
docs/LICENSE.GPL
docs/LICENSE.txt
