Metadata-Version: 1.0
Name: Products.QuillsEnabledRemoteBlogging
Version: 1.7.0b1
Summary: MetaWeblogAPI support for QuillsEnabled
Home-page: http://plone.org/products/quills
Author: Quills Team
Author-email: quills-dev@lists.etria.com
License: GPL
Keywords: plone blogging
Platform: UNKNOWN
Classifier: Framework :: Plone
Classifier: Framework :: Zope2
Classifier: Framework :: Zope3
Classifier: Programming Language :: Python
Classifier: Topic :: Software Development :: Libraries :: Python Modules
